dending/__init__.py
dending/bin.py
dending/setup.py
DEndings-0.0.1.dist-info/METADATA
DEndings-0.0.1.dist-info/WHEEL
DEndings-0.0.1.dist-info/top_level.txt
DEndings-0.0.1.dist-info/RECORD
