Metadata-Version: 2.1
Name: DEndings
Version: 0.0.1
Summary: German verb endings in Python
Home-page: UNKNOWN
Author: Liem_Gradient
Author-email: limegradientyt@gmail.com
License: UNKNOWN
Keywords: python,first package
Platform: UNKNOWN
Classifier: Development Status :: 3 - Alpha
Classifier: Intended Audience :: Education
Classifier: Programming Language :: Python :: 2
Classifier: Programming Language :: Python :: 3
Classifier: Operating System :: MacOS :: MacOS X
Classifier: Operating System :: Microsoft :: Windows
